echoai_transformer_block/__init__.py
echoai_transformer_block/block.py
echoai_transformer_block/feedforward.py
echoai_transformer_block/multiheadattn.py
gpt_2/__init__.py
gpt_2/block.py
gpt_2/feedforward.py
gpt_2/multiheadattn.py
echoai_transformer_block-0.2.dist-info/METADATA
echoai_transformer_block-0.2.dist-info/WHEEL
echoai_transformer_block-0.2.dist-info/top_level.txt
echoai_transformer_block-0.2.dist-info/RECORD
