Metadata-Version: 2.1
Name: echoai-transformer-block
Version: 0.2
Summary: A package for Transformer blocks
Home-page: https://github.com/pratyakshagarwal/Echoai
Author: Echoai (pratyaksh agarwal)
Author-email: pratyakshagarwal93@gmail.com
License: MIT
Classifier: License :: OSI Approved :: MIT License
Classifier: Programming Language :: Python :: 3
Classifier: Programming Language :: Python :: 3.7
Classifier: Programming Language :: Python :: 3.8
Classifier: Programming Language :: Python :: 3.9
Requires-Dist: torch
